mongozen/__init__.py
mongozen/_version.py
mongozen/__pycache__/__init__.cpython-36.pyc
mongozen/__pycache__/_version.cpython-36.pyc
mongozen/__pycache__/core.cpython-36.pyc
mongozen/__pycache__/mongozen_objs.cpython-36.pyc
mongozen/__pycache__/param_inference.cpython-36.pyc
mongozen/__pycache__/shared.cpython-36.pyc
mongozen/__pycache__/util_constants.cpython-36.pyc
mongozen/matchop/__init__.py
mongozen/matchop/_matchop.py
mongozen/matchop/__pycache__/__init__.cpython-36.pyc
mongozen/matchop/__pycache__/_matchop.cpython-36.pyc
mongozen/queries/__init__.py
mongozen/queries/__pycache__/__init__.cpython-36.pyc
mongozen/queries/common/__init__.py
mongozen/queries/common/common.py
mongozen/queries/common/__pycache__/__init__.cpython-36.pyc
mongozen/queries/common/__pycache__/common.cpython-36.pyc
mongozen/queries/time/__init__.py
mongozen/queries/time/time.py
mongozen/queries/time/__pycache__/__init__.cpython-36.pyc
mongozen/queries/time/__pycache__/time.cpython-36.pyc
mongozen/util/__init__.py
mongozen/util/_util.py
mongozen/util/__pycache__/__init__.cpython-36.pyc
mongozen/util/__pycache__/_util.cpython-36.pyc
mongozen-0.0.6.dist-info/DESCRIPTION.rst
mongozen-0.0.6.dist-info/METADATA
mongozen-0.0.6.dist-info/RECORD
mongozen-0.0.6.dist-info/WHEEL
mongozen-0.0.6.dist-info/metadata.json
mongozen-0.0.6.dist-info/top_level.txt
tests/__init__.py
tests/test_cmds.py
tests/test_matchop.py
