Metadata-Version: 2.0
Name: mongozen
Version: 0.0.6
Summary: MongoDB utilities for Python
Home-page: https://github.com/shaypal5/mongozen
Author: Shay Palachy
Author-email: shay.palachy@gmail.com
License: UNKNOWN
Keywords: mongodb
Platform: any
Classifier: Development Status :: 4 - Beta
Classifier: License :: OSI Approved :: MIT License
Classifier: Programming Language :: Python
Classifier: Programming Language :: Python :: 3.5
Classifier: Programming Language :: Python :: 3.6
Classifier: Topic :: Software Development :: Libraries
Classifier: Topic :: Software Development :: Libraries :: Python Modules
Classifier: Intended Audience :: Developers
Requires-Python: >=3.5
Requires-Dist: pymongo
Requires-Dist: numpy
Requires-Dist: prettytable
Requires-Dist: pandas
Requires-Dist: strct (>=0.0.14)
Requires-Dist: utilitime (>=0.0.3)
Requires-Dist: comath (>=0.0.3)
Provides-Extra: test
Requires-Dist: pytest; extra == 'test'
Requires-Dist: coverage; extra == 'test'
Requires-Dist: pytest-cov; extra == 'test'
Requires-Dist: birch; extra == 'test'
Requires-Dist: pandas; extra == 'test'
Requires-Dist: pandas.compat; extra == 'test'
Requires-Dist: collective.checkdocs; extra == 'test'
Requires-Dist: pygments; extra == 'test'
